{
  "id": "LAB-ELECTRO-K-001",
  "name": "Hipocalemia Crítica",
  "category": "LAB",
  "subcategory": "ELECTROLYTES",
  "description": "Alerta para níveis críticos de potássio sérico <2.5 mEq/L com risco de arritmias fatais",
  "version": "1.0.0",
  "created": "2026-02-06",
  "updated": "2026-02-06",
  "author": "Critical Lab Specialist",
  "status": "active",
  "priority": "CRITICAL",
  "clinicalRationale": "Hipocalemia severa (<2.5 mEq/L) causa arritmias ventriculares potencialmente fatais incluindo torsades de pointes, fraqueza muscular grave, íleo paralítico, e pode levar a parada cardíaca. Reposição urgente é mandatória com monitoramento ECG contínuo.",
  "inputVariables": [
    {
      "name": "potassio",
      "type": "number",
      "unit": "mEq/L",
      "description": "Potássio sérico",
      "required": true,
      "normalRange": "3.5-5.0 mEq/L"
    }
  ],
  "outputVariables": [
    {
      "name": "nivelAlerta",
      "type": "string",
      "values": ["Alerta", "Atencao", "OK"]
    },
    {
      "name": "urgencia",
      "type": "string",
      "values": ["IMEDIATA", "ALTA", "MEDIA", "BAIXA"]
    },
    {
      "name": "classificacao",
      "type": "string"
    },
    {
      "name": "tendencia",
      "type": "string"
    },
    {
      "name": "acaoRequerida",
      "type": "string"
    },
    {
      "name": "justificativaCientifica",
      "type": "string"
    }
  ],
  "references": [
    "UpToDate: Causes and evaluation of hypokalemia in adults",
    "ACC/AHA Guidelines for Management of Electrolyte Abnormalities",
    "Critical Lab Values: Hypokalemia <2.5 mEq/L requires immediate notification"
  ],
  "tags": ["critical-lab", "electrolytes", "potassium", "hypokalemia", "arrhythmia", "cardiac-risk"]
}
