<?xml version="1.0" encoding="UTF-8"?>
<definitions xmlns="https://www.omg.org/spec/DMN/20191111/MODEL/"
             xmlns:dmndi="https://www.omg.org/spec/DMN/20191111/DMNDI/"
             xmlns:dc="http://www.omg.org/spec/DMN/20180521/DC/"
             id="Definitions_30907020"
             name="Estudo Eletrofisiológico Intracavitário Diagnóstico"
             namespace="http://camunda.org/schema/1.0/dmn">

  <!--
    ===============================================================================
    TUSS: 30907020
    Procedimento: Estudo Eletrofisiológico Intracavitário Diagnóstico
    Versão: 3.0.0-TIER2-LEAN
    Data: 2026-02-08
    ===============================================================================
    INDICAÇÕES CLÍNICAS (DUT/ANS):
    - Arritmias cardíacas complexas sem diagnóstico definitivo por métodos não invasivos
    - Síncope inexplicada recorrente com suspeita de causa arrítmica
    - Avaliação pré-ablação para mapeamento eletrofisiológico detalhado
    - Taquicardia supraventricular com mecanismo não esclarecido
    - Investigação de bradicardia sintomática com dúvida diagnóstica
    - Avaliação de risco em pacientes assintomáticos com pré-excitação (WPW)
    - Estratificação de risco de morte súbita em miocardiopatias selecionadas

    CONTRAINDICAÇÕES:
    - Arritmia com causa reversível claramente identificada (distúrbio eletrolítico, isquemia aguda)
    - ECG diagnóstico suficiente com conduta terapêutica clara
    - Coagulopatia não corrigida ou INR >3.0
    - Infecção ativa ou febre de origem indeterminada
    - Trombo intracavitário documentado
    - Impossibilidade de acesso vascular adequado
    - Recusa do paciente após esclarecimento completo

    DOCUMENTAÇÃO OBRIGATÓRIA:
    - ECG de 12 derivações com documentação da arritmia (quando possível)
    - Holter 24-48h ou monitor de eventos com registro de episódios
    - Ecocardiograma transtorácico recente (excluir cardiopatia estrutural)
    - Relatório médico detalhando indicação e objetivos do estudo
    - Coagulograma completo (TP, INR, TTPA, plaquetas)
    - Documentação de falha ou limitação de métodos não invasivos
    - Termo de consentimento informado detalhado

    REFERÊNCIAS TÉCNICAS:
    - SOBRAC Diretrizes Brasileiras de Estudos Eletrofisiológicos 2023
    - HRS/EHRA/APHRS Expert Consensus on Catheter Ablation 2022
    - ACC/AHA/HRS Guideline for the Evaluation and Management of Patients With Syncope 2021
    - ANS RN 465/2021 - Rol de Procedimentos e Eventos em Saúde
    ===============================================================================
  -->

  <decision id="Decision_30907020" name="Regra Clínica - Estudo Eletrofisiológico">
    <decisionTable id="DecisionTable_30907020" hitPolicy="FIRST">

      <input id="Input_condicaoPaciente" label="Condição do Paciente">
        <inputExpression id="InputExpression_condicaoPaciente" typeRef="string">
          <text>condicaoPaciente</text>
        </inputExpression>
        <inputValues id="InputValues_condicaoPaciente">
          <text>"ArritmiasComplexas","SincopeInexplicada","AvaliacaoPreAblacao","TaquicardiaSupraventricular","BradicardiaInvestigacao"</text>
        </inputValues>
      </input>

      <input id="Input_historicoClinico" label="Histórico Clínico Documentado">
        <inputExpression id="InputExpression_historicoClinico" typeRef="string">
          <text>historicoClinico</text>
        </inputExpression>
        <inputValues id="InputValues_historicoClinico">
          <text>"Adequado","Incompleto","NaoDocumentado"</text>
        </inputValues>
      </input>

      <input id="Input_classeIndicacao" label="Classe de Indicação (Diretrizes)">
        <inputExpression id="InputExpression_classeIndicacao" typeRef="string">
          <text>classeIndicacao</text>
        </inputExpression>
        <inputValues id="InputValues_classeIndicacao">
          <text>"Classe I","Classe IIa","Classe IIb","Classe III"</text>
        </inputValues>
      </input>

      <input id="Input_feVE" label="Fração de Ejeção do Ventrículo Esquerdo">
        <inputExpression id="InputExpression_feVE" typeRef="string">
          <text>feVE</text>
        </inputExpression>
        <inputValues id="InputValues_feVE">
          <text>"<15%","15-30%","30-35%","35-50%",">50%","NaoAvaliada"</text>
        </inputValues>
      </input>

      <input id="Input_expectativaVidaSuperior1Ano" label="Expectativa de Vida Superior a 1 Ano">
        <inputExpression id="InputExpression_expectativaVidaSuperior1Ano" typeRef="boolean">
          <text>expectativaVidaSuperior1Ano</text>
        </inputExpression>
      </input>

      <output id="Output_resultado" label="Resultado" name="resultado" typeRef="string">
        <outputValues id="OutputValues_resultado">
          <text>"Aprovado","Reprovado","Pendente"</text>
        </outputValues>
      </output>

      <output id="Output_observacao" label="Observação Clínica" name="observacao" typeRef="string" />

      <output id="Output_fundamentacao" label="Fundamentação Técnica" name="fundamentacao" typeRef="string" />

      <output id="Output_alertasDesperdicio" label="Alertas de Desperdicio" name="alertasDesperdicio" typeRef="string">
        <outputValues id="OutputValues_alertasDesperdicio">
          <text>"NENHUM","DUP","FREQ","ESC","DOC","PROT","MULTI"</text>
        </outputValues>
      </output>

      <output id="Output_acaoRecomendada" label="Acao Recomendada" name="acaoRecomendada" typeRef="string">
        <outputValues id="OutputValues_acaoRecomendada">
          <text>"APROVAR","NEGAR","SOLICITAR_INFO","AGUARDAR_PRAZO","SUGERIR_ALTERNATIVA"</text>
        </outputValues>
      </output>

      <rule id="Rule_Contraind_30907020_1">
        <description>Contraindicação: Classe de indicação III - EEF não recomendado</description>
        <inputEntry id="InputEntry_condicaoPaciente_R1">
          <text>-</text>
        </inputEntry>
        <inputEntry id="InputEntry_historicoClinico_R1">
          <text>-</text>
        </inputEntry>
        <inputEntry id="InputEntry_classeIndicacao_R1">
          <text>"Classe III"</text>
        </inputEntry>
        <inputEntry id="InputEntry_feVE_R1">
          <text>-</text>
        </inputEntry>
        <inputEntry id="InputEntry_expectativaVidaSuperior1Ano_R1">
          <text>-</text>
        </inputEntry>
        <outputEntry id="OutputEntry_resultado_R1">
          <text>"Reprovado"</text>
        </outputEntry>
        <outputEntry id="OutputEntry_observacao_R1">
          <text>"Procedimento contraindicado - Classe III das diretrizes SOBRAC/HRS"</text>
        </outputEntry>
        <outputEntry id="OutputEntry_fundamentacao_R1">
          <text>"SOBRAC 2023 Classe III - EEF não é recomendado quando há diagnóstico estabelecido por métodos não invasivos, causa reversível identificada, ou quando não alterará a conduta terapêutica. Risco injustificado"</text>
        </outputEntry>
        <outputEntry id="OE_R1_alertasDesperdicio">
          <text>"PROT"</text>
        </outputEntry>
        <outputEntry id="OE_R1_acaoRecomendada">
          <text>"NEGAR"</text>
        </outputEntry>
      </rule>

      <rule id="Rule_Contraind_30907020_2">
        <description>Contraindicação: Expectativa de vida <1 ano - procedimento não justificado</description>
        <inputEntry id="InputEntry_condicaoPaciente_R2">
          <text>-</text>
        </inputEntry>
        <inputEntry id="InputEntry_historicoClinico_R2">
          <text>-</text>
        </inputEntry>
        <inputEntry id="InputEntry_classeIndicacao_R2">
          <text>-</text>
        </inputEntry>
        <inputEntry id="InputEntry_feVE_R2">
          <text>-</text>
        </inputEntry>
        <inputEntry id="InputEntry_expectativaVidaSuperior1Ano_R2">
          <text>false</text>
        </inputEntry>
        <outputEntry id="OutputEntry_resultado_R2">
          <text>"Reprovado"</text>
        </outputEntry>
        <outputEntry id="OutputEntry_observacao_R2">
          <text>"Expectativa de vida limitada - EEF não proporcionará benefício clínico significativo"</text>
        </outputEntry>
        <outputEntry id="OutputEntry_fundamentacao_R2">
          <text>"HRS/EHRA 2022 - Procedimento invasivo não é recomendado quando a expectativa de vida é <1 ano devido a comorbidades não cardíacas, exceto se alterar manejo imediato de arritmia sintomática com risco de vida"</text>
        </outputEntry>
        <outputEntry id="OE_R2_alertasDesperdicio">
          <text>"PROT"</text>
        </outputEntry>
        <outputEntry id="OE_R2_acaoRecomendada">
          <text>"NEGAR"</text>
        </outputEntry>
      </rule>

      <rule id="Rule_Pendente_30907020_3">
        <description>Pendência: Documentação clínica inadequada - complementação necessária</description>
        <inputEntry id="InputEntry_condicaoPaciente_R3">
          <text>-</text>
        </inputEntry>
        <inputEntry id="InputEntry_historicoClinico_R3">
          <text>"NaoDocumentado","Incompleto"</text>
        </inputEntry>
        <inputEntry id="InputEntry_classeIndicacao_R3">
          <text>-</text>
        </inputEntry>
        <inputEntry id="InputEntry_feVE_R3">
          <text>-</text>
        </inputEntry>
        <inputEntry id="InputEntry_expectativaVidaSuperior1Ano_R3">
          <text>-</text>
        </inputEntry>
        <outputEntry id="OutputEntry_resultado_R3">
          <text>"Pendente"</text>
        </outputEntry>
        <outputEntry id="OutputEntry_observacao_R3">
          <text>"Documentação insuficiente - solicitar ECG, Holter/monitor eventos, ecocardiograma, coagulograma"</text>
        </outputEntry>
        <outputEntry id="OutputEntry_fundamentacao_R3">
          <text>"ANS RN 465/2021 - Necessária documentação completa: ECG 12 derivações, Holter 24-48h ou monitor de eventos, ecocardiograma transtorácico, coagulograma (TP/INR/TTPA/plaquetas), relatório médico justificando indicação"</text>
        </outputEntry>
        <outputEntry id="OE_R3_alertasDesperdicio">
          <text>"DOC"</text>
        </outputEntry>
        <outputEntry id="OE_R3_acaoRecomendada">
          <text>"SOLICITAR_INFO"</text>
        </outputEntry>
      </rule>

      <rule id="Rule_Aprovacao_30907020_4">
        <description>Aprovação: Arritmias complexas sem diagnóstico por métodos não invasivos - Classe I</description>
        <inputEntry id="InputEntry_condicaoPaciente_R4">
          <text>"ArritmiasComplexas"</text>
        </inputEntry>
        <inputEntry id="InputEntry_historicoClinico_R4">
          <text>"Adequado"</text>
        </inputEntry>
        <inputEntry id="InputEntry_classeIndicacao_R4">
          <text>"Classe I"</text>
        </inputEntry>
        <inputEntry id="InputEntry_feVE_R4">
          <text>-</text>
        </inputEntry>
        <inputEntry id="InputEntry_expectativaVidaSuperior1Ano_R4">
          <text>true</text>
        </inputEntry>
        <outputEntry id="OutputEntry_resultado_R4">
          <text>"Aprovado"</text>
        </outputEntry>
        <outputEntry id="OutputEntry_observacao_R4">
          <text>"Arritmia complexa documentada sem diagnóstico por ECG/Holter - EEF aprovado para esclarecimento diagnóstico"</text>
        </outputEntry>
        <outputEntry id="OutputEntry_fundamentacao_R4">
          <text>"SOBRAC 2023 Classe I - EEF está indicado em pacientes com arritmias documentadas que não foram adequadamente diagnosticadas por métodos não invasivos e cuja caracterização é necessária para guiar terapêutica (medicamentosa, ablação, dispositivo)"</text>
        </outputEntry>
        <outputEntry id="OE_R4_alertasDesperdicio">
          <text>"NENHUM"</text>
        </outputEntry>
        <outputEntry id="OE_R4_acaoRecomendada">
          <text>"APROVAR"</text>
        </outputEntry>
      </rule>

      <rule id="Rule_Aprovacao_30907020_5">
        <description>Aprovação: Síncope inexplicada recorrente com suspeita arrítmica - Classe I</description>
        <inputEntry id="InputEntry_condicaoPaciente_R5">
          <text>"SincopeInexplicada"</text>
        </inputEntry>
        <inputEntry id="InputEntry_historicoClinico_R5">
          <text>"Adequado"</text>
        </inputEntry>
        <inputEntry id="InputEntry_classeIndicacao_R5">
          <text>"Classe I","Classe IIa"</text>
        </inputEntry>
        <inputEntry id="InputEntry_feVE_R5">
          <text>-</text>
        </inputEntry>
        <inputEntry id="InputEntry_expectativaVidaSuperior1Ano_R5">
          <text>true</text>
        </inputEntry>
        <outputEntry id="OutputEntry_resultado_R5">
          <text>"Aprovado"</text>
        </outputEntry>
        <outputEntry id="OutputEntry_observacao_R5">
          <text>"Síncope recorrente inexplicada com cardiopatia estrutural ou ECG anormal - EEF aprovado"</text>
        </outputEntry>
        <outputEntry id="OutputEntry_fundamentacao_R5">
          <text>"ACC/AHA/HRS Syncope 2021 Classe I - EEF está indicado em pacientes com síncope recorrente inexplicada e cardiopatia estrutural (FEVE reduzida, miocardiopatia) ou ECG sugestivo de arritmia (BAV 2º grau Mobitz I, BRD+BFAE, pré-excitação), para avaliação de bradiarritmias ou taquiarritmias indutíveis"</text>
        </outputEntry>
        <outputEntry id="OE_R5_alertasDesperdicio">
          <text>"NENHUM"</text>
        </outputEntry>
        <outputEntry id="OE_R5_acaoRecomendada">
          <text>"APROVAR"</text>
        </outputEntry>
      </rule>

      <rule id="Rule_Aprovacao_30907020_6">
        <description>Aprovação: Avaliação pré-ablação para mapeamento eletrofisiológico - Classe I</description>
        <inputEntry id="InputEntry_condicaoPaciente_R6">
          <text>"AvaliacaoPreAblacao","TaquicardiaSupraventricular"</text>
        </inputEntry>
        <inputEntry id="InputEntry_historicoClinico_R6">
          <text>"Adequado"</text>
        </inputEntry>
        <inputEntry id="InputEntry_classeIndicacao_R6">
          <text>"Classe I"</text>
        </inputEntry>
        <inputEntry id="InputEntry_feVE_R6">
          <text>-</text>
        </inputEntry>
        <inputEntry id="InputEntry_expectativaVidaSuperior1Ano_R6">
          <text>true</text>
        </inputEntry>
        <outputEntry id="OutputEntry_resultado_R6">
          <text>"Aprovado"</text>
        </outputEntry>
        <outputEntry id="OutputEntry_observacao_R6">
          <text>"EEF diagnóstico pré-ablação para mapeamento detalhado do substrato arrítmico - aprovado"</text>
        </outputEntry>
        <outputEntry id="OutputEntry_fundamentacao_R6">
          <text>"HRS/EHRA/APHRS 2022 Classe I - EEF diagnóstico está indicado antes de ablação para caracterização precisa do mecanismo de taquicardia supraventricular (TRNAV, via acessória, flutter atrial, TA focal), mapeamento eletrofisiológico e planejamento do procedimento ablativo"</text>
        </outputEntry>
        <outputEntry id="OE_R6_alertasDesperdicio">
          <text>"NENHUM"</text>
        </outputEntry>
        <outputEntry id="OE_R6_acaoRecomendada">
          <text>"APROVAR"</text>
        </outputEntry>
      </rule>

      <rule id="Rule_Aprovacao_30907020_7">
        <description>Aprovação: Investigação de bradicardia ou estratificação de risco - Classe IIa</description>
        <inputEntry id="InputEntry_condicaoPaciente_R7">
          <text>"BradicardiaInvestigacao","ArritmiasComplexas"</text>
        </inputEntry>
        <inputEntry id="InputEntry_historicoClinico_R7">
          <text>"Adequado"</text>
        </inputEntry>
        <inputEntry id="InputEntry_classeIndicacao_R7">
          <text>"Classe IIa"</text>
        </inputEntry>
        <inputEntry id="InputEntry_feVE_R7">
          <text>-</text>
        </inputEntry>
        <inputEntry id="InputEntry_expectativaVidaSuperior1Ano_R7">
          <text>true</text>
        </inputEntry>
        <outputEntry id="OutputEntry_resultado_R7">
          <text>"Aprovado"</text>
        </outputEntry>
        <outputEntry id="OutputEntry_observacao_R7">
          <text>"Bradicardia sintomática com dúvida diagnóstica ou estratificação de risco em miocardiopatia - EEF razoável"</text>
        </outputEntry>
        <outputEntry id="OutputEntry_fundamentacao_R7">
          <text>"SOBRAC 2023 Classe IIa - EEF é razoável para avaliação de bradicardia sintomática quando causa não esclarecida (doença do nó sinusal vs BAV), ou para estratificação de risco de morte súbita em miocardiopatias selecionadas (hipertrófica, arritmogênica, sarcoidose) quando indutibilidade de TV influenciará indicação de CDI"</text>
        </outputEntry>
        <outputEntry id="OE_R7_alertasDesperdicio">
          <text>"NENHUM"</text>
        </outputEntry>
        <outputEntry id="OE_R7_acaoRecomendada">
          <text>"APROVAR"</text>
        </outputEntry>
      </rule>

      <rule id="Rule_Fallback_30907020">
        <description>Regra padrão - Análise clínica individualizada necessária</description>
        <inputEntry id="InputEntry_condicaoPaciente_Fallback">
          <text>-</text>
        </inputEntry>
        <inputEntry id="InputEntry_historicoClinico_Fallback">
          <text>-</text>
        </inputEntry>
        <inputEntry id="InputEntry_classeIndicacao_Fallback">
          <text>-</text>
        </inputEntry>
        <inputEntry id="InputEntry_feVE_Fallback">
          <text>-</text>
        </inputEntry>
        <inputEntry id="InputEntry_expectativaVidaSuperior1Ano_Fallback">
          <text>-</text>
        </inputEntry>
        <outputEntry id="OutputEntry_resultado_Fallback">
          <text>"Pendente"</text>
        </outputEntry>
        <outputEntry id="OutputEntry_observacao_Fallback">
          <text>"Caso requer avaliação especializada - encaminhar para arritmologista com expertise em eletrofisiologia"</text>
        </outputEntry>
        <outputEntry id="OutputEntry_fundamentacao_Fallback">
          <text>"Situação não enquadrada nas regras padronizadas - necessária avaliação por arritmologista/eletrofisiologista para determinação da relação risco-benefício do EEF conforme SOBRAC 2023, considerando indicação clínica, risco do procedimento e impacto na conduta terapêutica"</text>
        </outputEntry>
        <outputEntry id="OE_Fallback_alertasDesperdicio">
          <text>"NENHUM"</text>
        </outputEntry>
        <outputEntry id="OE_Fallback_acaoRecomendada">
          <text>"SOLICITAR_INFO"</text>
        </outputEntry>
      </rule>

    </decisionTable>
  </decision>

  <dmndi:DMNDI>
    <dmndi:DMNDiagram>
      <dmndi:DMNShape dmnElementRef="Decision_30907020">
        <dc:Bounds height="80" width="180" x="160" y="100" />
      </dmndi:DMNShape>
    </dmndi:DMNDiagram>
  </dmndi:DMNDI>
</definitions>
