<?xml version="1.0" encoding="UTF-8"?>
<definitions xmlns="https://www.omg.org/spec/DMN/20191111/MODEL/" xmlns:dmndi="https://www.omg.org/spec/DMN/20191111/DMNDI/" xmlns:dc="http://www.omg.org/spec/DMN/20180521/DC/" xmlns:di="http://www.omg.org/spec/DMN/20180521/DI/" id="DDI_BLEED_015" name="DDI-BLEED-015: Ticagrelor + Aspirina  &gt; 100mg" namespace="http://camunda.org/schema/1.0/dmn">
  <decision id="ddi_bleed_015_decision" name="Ticagrelor + High-Dose Aspirin">
    <decisionTable id="ddi_bleed_015_table" hitPolicy="FIRST">
      <input id="input_medicamentos_ativos" label="Medicamentos Ativos">
        <inputExpression id="input_expr_medicamentos_ativos" typeRef="string">
          <text>medicamentosAtivos</text>
        </inputExpression>
      </input>
      <input id="input_medicamento_novo" label="Medicamento Novo">
        <inputExpression id="input_expr_medicamento_novo" typeRef="string">
          <text>medicamentoNovo</text>
        </inputExpression>
      </input>
      <input id="input_dose_aspirina" label="Dose Aspirina (mg)">
        <inputExpression id="input_expr_dose" typeRef="number">
          <text>doseAspirina</text>
        </inputExpression>
      </input>

      <output id="output_nivel_alerta" name="nivelAlerta" typeRef="string">
        <outputValues>
          <text>"Alerta","Atencao","Informativo","OK"</text>
        </outputValues>
      </output>
      <output id="output_urgencia" name="urgencia" typeRef="string">
        <outputValues>
          <text>"IMEDIATA","URGENTE","ROTINA"</text>
        </outputValues>
      </output>
      <output id="output_medicamentos_conflitantes" name="medicamentosConflitantes" typeRef="string" />
      <output id="output_mecanismo_interacao" name="mecanismoInteracao" typeRef="string" />
      <output id="output_acao_requerida" name="acaoRequerida" typeRef="string" />

      <!-- Rule 1: Ticagrelor + Aspirina >100mg -->
      <rule id="rule_ticag_asa_alta">
        <inputEntry id="input_medicamentos_ticag">
          <text>list contains(medicamentosAtivos, "TICAGRELOR")</text>
        </inputEntry>
        <inputEntry id="input_novo_asa">
          <text>"ASPIRINA" or "AAS" or "ACIDO ACETILSALICILICO"</text>
        </inputEntry>
        <inputEntry id="input_dose_alta">
          <text>&gt; 100</text>
        </inputEntry>
        <outputEntry id="output_alerta_alta">
          <text>"Atencao"</text>
        </outputEntry>
        <outputEntry id="output_urgencia_alta">
          <text>"ROTINA"</text>
        </outputEntry>
        <outputEntry id="output_conflitantes_alta">
          <text>"Ticagrelor + Aspirina &gt;100mg"</text>
        </outputEntry>
        <outputEntry id="output_mecanismo_alta">
          <text>"DOSE SUBÓTIMA: PLATO trial demonstrou ticagrelor + aspirina 75-100mg SUPERIOR a doses maiores (>300mg). Aspirina alta dose (>100mg) AUMENTA sangramento SEM benefício isquêmico adicional. Mecanismo: aspirina >100mg não aumenta inibição COX-1 plaquetária mas aumenta efeitos sistêmicos pró-hemorrágicos (lesão mucosa GI, inibição COX-2 renal)."</text>
        </outputEntry>
        <outputEntry id="output_acao_alta">
          <text>"REDUZIR aspirina para 75-100mg/dia: (1) Dose ideal: 81-100mg/dia (eficácia MÁXIMA, menos sangramento), (2) NUNCA >100mg com ticagrelor (sem benefício, mais sangramento), (3) IBP se fatores risco GI (idade >65, úlcera prévia): omeprazol 20mg/dia, (4) Monitorar sinais sangramento (melena, hematomas). Nota: ticagrelor já MUITO potente (inibição P2Y12 90%), aspirina baixa dose suficiente."</text>
        </outputEntry>
      </rule>

      <!-- Rule 2: Ticagrelor + Aspirina dose adequada (≤100mg) -->
      <rule id="rule_ticag_asa_ok">
        <inputEntry id="input_medicamentos_ticag_ok">
          <text>list contains(medicamentosAtivos, "TICAGRELOR")</text>
        </inputEntry>
        <inputEntry id="input_novo_asa_ok">
          <text>"ASPIRINA" or "AAS" or "ACIDO ACETILSALICILICO"</text>
        </inputEntry>
        <inputEntry id="input_dose_ok">
          <text>&lt;= 100</text>
        </inputEntry>
        <outputEntry id="output_alerta_ok">
          <text>"Informativo"</text>
        </outputEntry>
        <outputEntry id="output_urgencia_ok">
          <text>"ROTINA"</text>
        </outputEntry>
        <outputEntry id="output_conflitantes_ok">
          <text>"Ticagrelor + Aspirina dose adequada"</text>
        </outputEntry>
        <outputEntry id="output_mecanismo_ok">
          <text>"DOSE ADEQUADA: Ticagrelor 90mg 12/12h + aspirina 75-100mg/dia = esquema PLATO (redução mortalidade CV 16% vs clopidogrel). Risco sangramento MAIOR aumentado (~12% vs 11.2% clopidogrel) mas aceitável dado benefício."</text>
        </outputEntry>
        <outputEntry id="output_acao_ok">
          <text>"MANTER esquema atual: (1) Ticagrelor 90mg 12/12h + aspirina 75-100mg/dia, (2) IBP se fatores risco GI (omeprazol 20mg/dia - sem interação ticagrelor), (3) Monitorar efeitos colaterais ticagrelor: dispneia (10-15% - geralmente autolimitada, raramente requer suspensão), bradicardia (pausas >3s em 5-10%), (4) Duração: 12 meses pós-SCA (PLATO protocolo), (5) Advertir paciente: ticagrelor REVERSÍVEL (suspender 5 dias antes cirurgia eletiva)."</text>
        </outputEntry>
      </rule>

      <!-- Fallback Rule -->
      <rule id="rule_fallback">
        <inputEntry id="input_fallback_1">
          <text>-</text>
        </inputEntry>
        <inputEntry id="input_fallback_2">
          <text>-</text>
        </inputEntry>
        <inputEntry id="input_fallback_3">
          <text>-</text>
        </inputEntry>
        <outputEntry id="output_fallback_1">
          <text>"OK"</text>
        </outputEntry>
        <outputEntry id="output_fallback_2">
          <text>"ROTINA"</text>
        </outputEntry>
        <outputEntry id="output_fallback_3">
          <text>""</text>
        </outputEntry>
        <outputEntry id="output_fallback_4">
          <text>""</text>
        </outputEntry>
        <outputEntry id="output_fallback_5">
          <text>""</text>
        </outputEntry>
      </rule>
    </decisionTable>
  </decision>
</definitions>
