{
  "ruleCode": "RECV-NEGO-001",
  "ruleName": "Desconto Quitacao",
  "category": "RECV",
  "subcategory": "NEGO",
  "specialty": "Financeiro",
  "version": "1.0.0",
  "status": "active",
  "hitPolicy": "FIRST",
  "perspective": "HOSPITAL",
  "createdAt": "2026-02-06T00:00:00Z",
  "updatedAt": "2026-02-06T00:00:00Z",
  "inputs": [
    {
      "name": "valorOriginal",
      "type": "number",
      "label": "Valor Original (R$)",
      "required": true,
      "description": "Valor original da divida antes do desconto",
      "validation": {"min": 0}
    },
    {
      "name": "percentualDesconto",
      "type": "number",
      "label": "Percentual de Desconto (%)",
      "required": true,
      "description": "Percentual de desconto proposto (0-100)",
      "validation": {"min": 0, "max": 100}
    },
    {
      "name": "prazoQuitacao",
      "type": "number",
      "label": "Prazo para Quitacao (dias)",
      "required": true,
      "description": "Prazo em dias para pagamento com desconto",
      "validation": {"min": 1}
    },
    {
      "name": "historicoOperadora",
      "type": "string",
      "label": "Historico da Operadora",
      "required": true,
      "allowedValues": ["REGULAR", "IRREGULAR", "INADIMPLENTE"],
      "description": "Classificacao do historico de pagamento da operadora"
    }
  ],
  "outputs": [
    {
      "name": "resultado",
      "type": "string",
      "label": "Resultado",
      "allowedValues": ["Prosseguir", "Bloquear", "Alertar", "Revisar"],
      "description": "Decisao sobre aprovacao do desconto"
    },
    {
      "name": "observacao",
      "type": "string",
      "label": "Observacao",
      "description": "Mensagem explicativa da decisao"
    },
    {
      "name": "acaoRecomendada",
      "type": "string",
      "label": "Acao Recomendada",
      "allowedValues": ["APROVAR_DESCONTO", "REJEITAR", "CONTRAPROPOSTA", "ESCALAR_DIRETORIA"],
      "description": "Acao recomendada para tratamento da proposta"
    },
    {
      "name": "descontoMaximoSugerido",
      "type": "number",
      "label": "Desconto Maximo Sugerido (%)",
      "description": "Percentual maximo de desconto sugerido para contraproposta"
    }
  ],
  "indications": [
    "Desconto ate 15% para quitacao em ate 15 dias",
    "Desconto ate 20% para quitacao em ate 30 dias",
    "Operadora com historico de pagamento regular",
    "Valor de divida elevado justifica negociacao"
  ],
  "contraindications": [
    "Desconto superior a 30% do valor original",
    "Prazo de quitacao superior a 30 dias com desconto alto",
    "Operadora em situacao de inadimplencia grave"
  ],
  "references": [
    "CDC Art. 52 - Desconto para pagamento antecipado",
    "CPC Art. 924 - Quitacao de dividas",
    "ANS RN 395/2016 - Ressarcimento ao SUS"
  ],
  "tags": ["negociacao", "desconto", "quitacao", "financeiro", "operadora"],
  "compliance": {
    "regulations": ["CDC", "CPC", "ANS"],
    "auditRequired": true,
    "retentionPeriodDays": 1825
  },
  "metrics": {
    "expectedSuccessRate": 0.75,
    "avgProcessingTimeDays": 2
  },
  "changelog": [
    {
      "version": "1.0.0",
      "date": "2026-02-06",
      "changes": "Versao inicial - Regra de desconto para quitacao",
      "author": "Sistema"
    }
  ]
}
