{"id":"DDI-MODERATE-001","nome":"Estatina + Diltiazem/Verapamil - Limite de Dose","categoria":"Interacao Medicamentosa Moderada","subcategoria":"Hipolipemiante + BCC","severidade":"MODERADA","evidencia":"NIVEL 1 - FDA Dose Restrictions","referencias":["FDA Drug Safety Communication - Statins","Neuvonen PJ et al. Clin Pharmacol Ther. 2006;80:565-81"],"mecanismo":"Diltiazem e verapamil sao inibidores moderados de CYP3A4, aumentando AUC de estatinas CYP3A4-dependentes (sinvastatina 3-4x, atorvastatina 1.5-2x).","created_at":"2026-02-06","version":"1.0"}
