{
  "tussCode": "30101255",
  "procedure": "30101255_Curetagem_simples_de_lesoes_de_pele",
  "specialty": "Dermatologia",
  "version": "2.0.0",
  "createdAt": "2026-02-06T03:07:43Z",
  "updatedAt": "2026-02-06T03:07:43Z",
  "hitPolicy": "FIRST",
  "inputs": [
    {
      "name": "indicacaoClinica",
      "type": "string",
      "label": "Indicação Clínica"
    },
    {
      "name": "procedimentosConcomitantes",
      "type": "string",
      "label": "Procedimentos Concomitantes na Mesma Lesão"
    }
  ],
  "outputs": [
    {
      "name": "Status",
      "type": "string",
      "label": ""
    },
    {
      "name": "Justificativa",
      "type": "string",
      "label": ""
    }
  ],
  "references": [
    "TUSS ANS 2024",
    "Resolucao ANS 428/2017"
  ],
  "changelog": [
    {
      "version": "2.0.0",
      "date": "2026-02-06",
      "changes": "Metadados gerados automaticamente para migracao Camunda 8"
    }
  ]
}