{
  "id": "DDI-NEPHRO-009",
  "nome": "Aciclovir + Nefrotoxicos - Cristaluria e Lesao Renal Aguda",
  "categoria": "Interacao Medicamentosa Nefrotoxica",
  "subcategoria": "Antiviral + Nefrotóxicos",
  "severidade": "ALTA",
  "evidencia": "NIVEL 1 - Micromedex, Estudos de Farmacovigilancia",
  "referencias": [
    "Micromedex Drug Interactions",
    "Perazella MA. Am J Kidney Dis. 2005;46:1095-9",
    "Izzedine H et al. Kidney Int. 2005;67:2089-2100",
    "Brigden D et al. Am J Med. 1982;73(1A):210-6"
  ],
  "mecanismo": "Aciclovir e pouco soluvel em urina, precipitando como cristais nos tubulos renais, especialmente com: desidratacao, infusao rapida IV, altas doses, funcao renal prejudicada. Combinacao com outros nefrotóxicos potencializa lesao tubular.",
  "fatores_risco": [
    "Desidratacao",
    "Infusao IV rapida (<1 hora)",
    "Dose alta (>500mg)",
    "DRC previa (TFG <50)",
    "Uso concomitante de outros nefrotóxicos",
    "Idade >65 anos"
  ],
  "prevencao": [
    "Hidratacao vigorosa (2-3L/dia)",
    "Infusao IV lenta (minimo 1 hora)",
    "Ajuste de dose para funcao renal",
    "Evitar bolus IV"
  ],
  "ajuste_dose_renal": {
    "tfg_maior_50": "Dose padrao",
    "tfg_25_50": "Reduzir 50%",
    "tfg_10_25": "Reduzir 50%, intervalo 12h",
    "tfg_menor_10": "Reduzir 50%, intervalo 24h"
  },
  "created_at": "2026-02-06",
  "updated_at": "2026-02-06",
  "version": "1.0"
}
